{
   "abstract" : "PICA record processing",
   "author" : [
      "- Johann Rolschewski and Jakob Voss"
   ],
   "dynamic_config" : 0,
   "generated_by" : "Minilla/v3.1.7, CPAN::Meta::Converter version 2.150001",
   "license" : [
      "perl_5"
   ],
   "meta-spec" : {
      "url" : "http://search.cpan.org/perldoc?CPAN::Meta::Spec",
      "version" : "2"
   },
   "name" : "PICA-Data",
   "no_index" : {
      "directory" : [
         "t",
         "xt",
         "inc",
         "share",
         "eg",
         "examples",
         "author",
         "builder"
      ]
   },
   "prereqs" : {
      "configure" : {
         "requires" : {
            "Module::Build::Tiny" : "0.035"
         }
      },
      "develop" : {
         "requires" : {
            "Code::TidyAll" : "0",
            "Perl::Tidy" : "0",
            "Test::CPAN::Meta" : "0",
            "Test::Code::TidyAll" : "0.20",
            "Test::MinimumVersion::Fast" : "0.04",
            "Test::PAUSE::Permissions" : "0.07",
            "Test::Pod" : "1.41",
            "Test::Spellunker" : "v0.2.7",
            "Text::Diff" : "0"
         }
      },
      "runtime" : {
         "requires" : {
            "Carp" : "0",
            "Exporter" : "0",
            "IO::File" : "1.14",
            "IO::Handle" : "0",
            "List::Util" : "1.33",
            "Scalar::Util" : "0",
            "XML::LibXML" : "2",
            "XML::Writer" : "0",
            "perl" : "v5.14.1"
         }
      },
      "test" : {
         "requires" : {
            "File::Temp" : "0.2304",
            "IO::File" : "1.14",
            "Test::Deep" : "0.119",
            "Test::Exception" : "0.43",
            "Test::More" : "1.001003",
            "Test::Warn" : "0",
            "Test::XML" : "0.08",
            "YAML::Tiny" : "1.46"
         }
      }
   },
   "release_status" : "unstable",
   "resources" : {
      "bugtracker" : {
         "web" : "https://github.com/GBV/PICA-Data/issues"
      },
      "homepage" : "https://github.com/GBV/PICA-Data",
      "repository" : {
         "type" : "git",
         "url" : "git://github.com/GBV/PICA-Data.git",
         "web" : "https://github.com/GBV/PICA-Data"
      }
   },
   "version" : "1.20",
   "x_contributors" : [
      "Carsten Klee <klee@cpan.org>",
      "Jakob Voß <jakob.voss@gbv.de>",
      "Johann Rolschewski <johann@rolschewski.de>",
      "Johann Rolschewski <jorol@cpan.org>"
   ],
   "x_static_install" : 1
}
